{
    "IsSuccess": true,
    "ErrorCode": "200",
    "ErrorMessage": "Ok",
    "StatusCode": 200,
    "Data": {
        "Id": 27,
        "Title": "Accord de confidentialit\u00e9",
        "Title2": "",
        "ShortDesc": "The official language of the company is English. For a more detailed description of the company&#39;s activities, please visit the English version of the site. The information translated into languages \u200b\u200bother than English is for informational purposes only and does not have any legal force. The Company is not responsible for the accuracy of the information provided in other languages.<br \/><br \/>Ekol Global Markets respects each individual&#39;s right to privacy. We value our relationship with you and we are proud to protect your loyalty and respect by providing your security to every customer. The provisions of this notice apply to our former customers and our existing customers. Please read the following information.<br \/><br \/>1. GENERAL PROVISIONS<br \/><br \/>1.1 This Privacy Policy shall include the services of Ekol Global Markets (hereinafter referred to as the Company), officially represented by its Partners, including official services, financial and informational services, and so on. .) Customers.<br \/><br \/>1.2. By selecting the Company&#39;s services, the Client fully accepts all terms and conditions of publicly available documents. The same is the trade and investment transactions between the Customer and the Company, the use of various information materials, payments and transfers, etc. It also applies to interactions. Should the customer fail to comply with any conditions of the publicly available documentation package, he must discontinue any interference with the Company. If the Customer considers the terms of this Privacy Policy unacceptable for any reason, it shall cease all interactions with the Company, including terminating all financial transactions through the Company.<br \/><br \/>1.3. The present Privacy Policy declares one of the most important principles that the Company follows when serving its customers. The Company respects the right to privacy of each individual and legal unit, as well as those who wish to interact with the Company, regardless of whether they have a Customer. The terms of this Privacy Policy apply equally to the Company&#39;s former, current and future Customers. One of the most important priorities of the company is the relationship between the Company and its Customers. The Company adheres to and respects each Client individually and gives each Customer excellent security and confidentiality.<br \/><br \/>1.4. In the current Privacy Policy, the following basic terms and definitions are used:<br \/><br \/>1.4.1 Confidentiality (confidential information) is a legal right of an individual or legal entity to disclose private or personal information (data) or commercially classified information. In the relationship between the Company and the Client, confidentiality refers to the Company&#39;s commitment to ensure that the Company does not conceal and disclose the Customer&#39;s information as it provides service to the Customer.<br \/><br \/>1.4.2 Customer&#39;s personal information - information that characterizes, identifies, or verifies a customer or discloses specific details of his personality, financial terms and preferences. A more detailed description of this term can be found in the text of this Privacy Policy. The Privacy Policy is a complex measure, procedure, and action that provides for exceptional, authentic, and complete collection of complete, accurate and original information about the Customer. Information with the official (regulatory) organizations in accordance with the existing legislation and the conditions of the current Privacy Policy.<br \/><br \/>2. PERSONAL INFORMATION<br \/><br \/>2.1. When the Customer applies or maintains a live or demo account for the Company, the Company collects personal information for business purposes, such as evaluating the Client&#39;s financial requirements, processing the Customer&#39;s requests and opportunities, and informing the Customer about the products and services. This may interest him and provide effective and quality service to the Customer. This information can be of the following types:<br \/><br \/>2.1.1. Registration information - Information provided by the client about application forms and other documents (including electronic documents). This includes: name, surname, user name, contact information (postal address, phone number, e-mail, etc.), date of birth, profession, assets and revenues.<br \/><br \/>2.1.2. Transaction Information - Information between the Customer and the Company, or between the Customer and its Affiliates, as well as information between the Customer and the Company (unilateral or bilateral). Examples include Customer account balances, Trading activity, Customer requests, and Message responses used in the Company, including mail or log files. In this Privacy Policy, the term &quot;Affiliates of the Company&quot; refers to the companies owned or operated by the Company as well as a Company owned by the Company.<br \/><br \/>2.1.3. Verification Information - The information required to verify the Customer&#39;s identity (or the main contract in case the Customer is a legal unit), such as a passport or driver&#39;s license. Examples also include information from public records such as credit offices, information agencies, and address offices by the Company, or from other entities that are not affiliated with the Company. The Anti-Money Laundering Policy requires the Company to collect the necessary information and to take necessary measures to prevent the conversion and legalization of money (laundering) from illegal activities. In some cases, the Company has the right to request a document explaining the funds.<br \/><br \/>2.1.4. Information about subscriptions - information such as signals, alerts, news category and price subscriptions.<br \/><br \/>2.2. The Company does not collect or store any credit \/ debit card details of any customer.<br \/><br \/>2.3. The above is not included. The Company reserves the right to request further information from the Customer if necessary to comply with the existing legislation.<br \/><br \/>3. ABOUT &quot;COOKIES&quot;<br \/><br \/>3.1. Cookies are small files that contain information that a Web server (site) uses to track visitors. The company may set and access cookies on Client computers to assess which ads and promotions attract users to the Company Web site. The Company (or any of its departments) may use cookies to assess the Customer&#39;s interest in the Company&#39;s products and services and to track Customer activity on the Web server. The information collected by the Company and shared with its Subsidiaries is anonymous and not personally identifiable.<br \/><br \/>4. SECURITY TECHNOLOGIES<br \/><br \/>4.1. The Company uses Secure Sockets Layer (SSL) encryption technology to protect specific information sent by its Customers. This technology prevents the Customer from capturing his \/ her information by anyone outside the Company. The company is working hard to ensure that Web servers (sites) are secure and meet industry standards. The company also uses other security measures, such as firewalls, authentication systems (eg passwords and personal identification numbers) and access control mechanisms, to control unauthorized access to systems and data.<br \/><br \/>4.2. At its sole discretion, the Company reserves the right to select technologies and methods of data protection and to cooperate with contractors that appear to be reliable for the Company.<br \/><br \/>4.3. In line with the recommendations of the Payment Card Industry Safety Standards Council, customer card details are protected using Transfer Layer encryption - TLS 1.2 and the application layer with AES algorithm and key length of 256 bits.<br \/><br \/>5. SHARING OF THE COMPANY WITH THE SUBSIDIARIES<br \/><br \/>5.1. The Company may share the personal information described above with its affiliates for business purposes, such as providing service to the Client&#39;s accounts and informing them of new products and services as permitted by applicable law.<br \/><br \/>5.2. Affiliate partners may access Customer specific information upon request by the Company and subject to the mandatory approval by the individual Customer. Each access to Customer&#39;s personal information by a partner partner is recorded in a log that can be viewed by the Customer. This log includes: time, spouse&#39;s name and type of information sought.<br \/>6. SHARING INFORMATION WITH THIRD PARTIES<br \/><br \/>6.1. The Company does not disclose the Customer&#39;s personal information to third parties except as provided in this Privacy Policy. Third-party disclosures may include sharing such information with the Company&#39;s Non-Partner Partners, which provide technical support services to Client accounts, or facilitate the Company and Customer agreements with the Company, including those providing professional, legal or accounting advice to the Company. The non-affiliated Partners who assist the Company in providing services to customers to maintain the confidentiality of such information and the purposes for which such personal information is provided solely by the Company and solely by the Company.<br \/><br \/>6.2. The Company may also disclose Customer&#39;s personal information to third parties in accordance with Customer&#39;s instructions or in accordance with Customer&#39;s express approval. The Company also informs the Client that he will not sell, temporarily, or distribute the Customer&#39;s Personal Information under any circumstances whatsoever at no cost to the Customer.<br \/><br \/>7. LEGISLATION<br \/><br \/>7.1. Under limited circumstances, the Company may disclose the Customer&#39;s personal information to third parties in accordance with or permitted by applicable laws and regulations. The Company may disclose personal information to comply with subpoena or other official requests and to cooperate with regulatory authorities and law enforcement agencies as necessary to protect Company rights or property.<br \/><br \/>7.2. Except as provided in this Privacy Policy, the Company shall not use the Customer&#39;s personal information for any other purpose, unless expressly stated on the date of disclosure by Customer or unless expressly authorized to do so by the Company.<br \/><br \/>The Company has the right to use the Customer&#39;s personal information when it is disclosed by the Customer or when the Company expressly expressly expressly expressly expresses the Customer&#39;s warranty.<br \/><br \/>8. OPT OUTPUT<br \/><br \/>8.1. The Customer may refuse to provide any Personal information that the Company may request. However, failure to do so may result in the Company being unable to open or maintain an account or to provide other services to the Client.<br \/><br \/>Although the Company makes every effort to ensure that the services provided to its Customers are based on accurate, complete and up-to-date information about them, the Customer may be able to assist in the matter immediately by notifying the company immediately when such a change is made.<br \/><br \/>8.2. If the Customer does not want his \/ her personal information to be disclosed to third parties specified in this Privacy Policy, the Customer must contact the Company through a specific contact form.<br \/><br \/>9. Changes<br \/><br \/>9.1. The Company reserves the right to make changes to this Privacy Policy. In particular, this may be the case in cases in which the present edition of the Privacy Policy is not explained directly or indirectly, or in the event of a rule or law requiring such a change or addition.<br \/><br \/>9.2. Agenda procedure:<br \/><br \/>9.2.1 In the event of changes and \/ or additions, the Company shall inform the Customers by sending a corresponding message via the internal mail system on the official website.<br \/><br \/>9.2.2 The publication of the relevant notice on the Company Web Site and the sending of messages by internal mail shall be deemed to be an Adequate Privacy Policy of the changes in cases where the Customer has read or not considered the relevant text or ignored it.<br \/><br \/>9.2.3 The amended document shall enter into force after five (five) full astronomical days (120 hours) after the notice is published on the Company&#39;s Web site, before the notice is only informative.<br \/><br \/>9.2.4 The amended document applies to all registered accounts immediately after publication (irrespective of any other accounts previously registered and owned by the owner). The amended document shall apply to the trading accounts recorded prior to the effective date of that document.<br \/><br \/>9.2.5 In the case of a rule of law requiring amendments and \/ or additions in accordance with this Privacy Policy, the rule of law shall apply immediately after the entry into force of the relevant legal regulation. required or no modification has been made. The regulations of the current Privacy Policy, which are either newly introduced or unlawful, become null and void when the relevant amendments to the above mentioned document become effective.<br \/><br \/>10. ACKNOWLEDGE CONDITIONS BY CLIENT<br \/><br \/>10.1. Being a customer of the company and actively using its services (including brokerage services and information services), using software and \/ or hardware to conduct professional activities in financial markets, I accept the Privacy Policy described in this Statement.<br \/><br \/>10.2. I accept all the provisions (provisions, chapters) of all the documents publicly disclosed by the Company during the use of any service of the Company, and in case of dispute, I will immediately discontinue use of the Company&#39;s services.",
        "LongDesc": "",
        "Link": null,
        "SeoTitle": "",
        "SeoDesc": "",
        "SeoTags": "confidentiality-agreement",
        "Sort": 0,
        "ModuleID": 6,
        "MainImages": "",
        "ListImages": "",
        "Banner1": "",
        "SubContent": [],
        "SubImages1": [],
        "SubImages2": null
    }
}